Workbook

Sheet Diagrama ER (corregido)

Sheet Inventario Modelo Lógico (corre
A1: Tablas resultantes del Diccionario Genérico (Modelo Lógico)
A2: # | B2: Tabla | C2: Descripción Tabla | D2: Observaciones
A3: 1 | B3: programa_academico | C3: Catálogo de programas académicos ofrecidos por la institución | D3: PK: id_programa | UK: codigo
A4: 2 | B4: habilidad | C4: Catálogo de habilidades que los usuarios pueden asociar a su perfil | D4: PK: id_habilidad | UK: nombre
A5: 3 | B5: interes | C5: Catálogo de áreas de interés disponibles para los usuarios | D5: PK: id_interes | UK: nombre
A6: 4 | B6: empresa | C6: Empresas registradas en la plataforma para publicar ofertas laborales | D6: PK: id_empresa
A7: 5 | B7: usuario | C7: Supertipo que agrupa a todos los tipos de usuarios de la red social | D7: PK: id_usuario | UK: email
A8: 6 | B8: estudiante | C8: Subtipo de usuario: estudiante activo de la institución | D8: PK: id_usuario | FK: id_usuario, id_programa
A9: 7 | B9: docente | C9: Subtipo de usuario: docente vinculado a la institución | D9: PK: id_usuario | FK: id_usuario
A10: 8 | B10: empleado | C10: Subtipo de usuario: empleado administrativo de la institución | D10: PK: id_usuario | FK: id_usuario
A11: 9 | B11: egresado | C11: Subtipo de usuario: graduado de la institución | D11: PK: id_usuario | FK: id_usuario, id_programa
A12: 10 | B12: publico_general | C12: Subtipo de usuario: persona externa sin vínculo institucional formal | D12: PK: id_usuario | FK: id_usuario
A13: 11 | B13: usuario_habilidad | C13: Tabla pivote N:M entre usuario y habilidad | D13: PK compuesta: id_usuario + id_habilidad
A14: 12 | B14: usuario_interes | C14: Tabla pivote N:M entre usuario y área de interés | D14: PK compuesta: id_usuario + id_interes
... A32: 30 | B32: reporte | C32: Reportes de contenido inapropiado realizados por usuarios | D32: PK: id_reporte | FK: id_reportante

Sheet Tipos de Dato
A1: Tipos de Datos - Tabla Comparativa
A2: # | B2: Tipo de Dato Genérico | C2: Tipos de Dato - PosgreSQL
A3: 1 | B3: AUTOINCREMENTABLE | C3: SERIAL
A4: 2 | B4: UUID | C4: UUID
A5: 3 | B5: ENTERO | C5: INT / SMALLINT
A6: 4 | B6: DECIMAL | C6: NUMERIC(p,s)
A7: 5 | B7: LÓGICO | C7: BOOLEAN
A8: 6 | B8: TEXTO | C8: TEXT
A9: 7 | B9: CARACTER | C9: VARCHAR(n)
A10: 8 | B10: FECHA | C10: DATE
A11: 9 | B11: FECHA_HORA | C11: TIMESTAMP
A12: 10 | B12: IMAGEN | C12: VARCHAR(255) — URL externa
A13: 11 | B13: AUDIO | C13: VARCHAR(255) — URL externa
A14: 12 | B14: URL | C14: VARCHAR(255)
... A18: 16 | B18: JSON | C18: JSONB

Sheet DICCIONARIO DATOS (Físico)
A2: DICCIONARIO DE DATOS FÍSICO — Red Social Estudiantil Pascualina
A3: INVENTARIO DE TABLAS
A4: # | B4: Tabla | C4: Descripción Tabla
A5: 1 | B5: ='Inventario Modelo Lógico (corre'!B3 -> programa_academico | C5: ='Inventario Modelo Lógico (corre'!C3 -> Catálogo de programas académicos ofrecidos por la institución
A6: 2 | B6: ='Inventario Modelo Lógico (corre'!B4 -> habilidad | C6: ='Inventario Modelo Lógico (corre'!C4 -> Catálogo de habilidades que los usuarios pueden asociar a su perfil
A7: 3 | B7: ='Inventario Modelo Lógico (corre'!B5 -> interes | C7: ='Inventario Modelo Lógico (corre'!C5 -> Catálogo de áreas de interés disponibles para los usuarios
A8: 4 | B8: ='Inventario Modelo Lógico (corre'!B6 -> empresa | C8: ='Inventario Modelo Lógico (corre'!C6 -> Empresas registradas en la plataforma para publicar ofertas laborales
A9: 5 | B9: ='Inventario Modelo Lógico (corre'!B7 -> usuario | C9: ='Inventario Modelo Lógico (corre'!C7 -> Supertipo que agrupa a todos los tipos de usuarios de la red social
A10: 6 | B10: ='Inventario Modelo Lógico (corre'!B8 -> estudiante | C10: ='Inventario Modelo Lógico (corre'!C8 -> Subtipo de usuario: estudiante activo de la institución
A11: 7 | B11: ='Inventario Modelo Lógico (corre'!B9 -> docente | C11: ='Inventario Modelo Lógico (corre'!C9 -> Subtipo de usuario: docente vinculado a la institución
A12: 8 | B12: ='Inventario Modelo Lógico (corre'!B10 -> empleado | C12: ='Inventario Modelo Lógico (corre'!C10 -> Subtipo de usuario: empleado administrativo de la institución
A13: 9 | B13: ='Inventario Modelo Lógico (corre'!B11 -> egresado | C13: ='Inventario Modelo Lógico (corre'!C11 -> Subtipo de usuario: graduado de la institución
A14: 10 | B14: ='Inventario Modelo Lógico (corre'!B12 -> publico_general | C14: ='Inventario Modelo Lógico (corre'!C12 -> Subtipo de usuario: persona externa sin vínculo institucional formal
A15: 11 | B15: ='Inventario Modelo Lógico (corre'!B13 -> usuario_habilidad | C15: ='Inventario Modelo Lógico (corre'!C13 -> Tabla pivote N:M entre usuario y habilidad
A16: 12 | B16: ='Inventario Modelo Lógico (corre'!B14 -> usuario_interes | C16: ='Inventario Modelo Lógico (corre'!C14 -> Tabla pivote N:M entre usuario y área de interés
... A34: 30 | B34: ='Inventario Modelo Lógico (corre'!B32 -> reporte | C34: ='Inventario Modelo Lógico (corre'!C32 -> Reportes de contenido inapropiado realizados por usuarios
A36: TABLAS EN DETALLE
A37: 1 | B37: Tabla | C37: =B5 -> programa_academico | E37: Descripción Tabla | G37: =C5 -> Catálogo de programas académicos ofrecidos por la institución | K37: Versión | L37: 1
A38: # | B38: Campo | C38: Descripción Campo | D38: Tipo Genérico | E38: Tipo PostgreSQL | F38: Tamaño | G38: Nulo | H38: PK | I38: FK | J38: UK | K38: Nota/Comentarios
A39: 1 | B39: id_programa | C39: Identificador único del programa | D39: AUTOINCREMENTABLE | E39: SERIAL | F39: SERIAL | G39: No | H39: S | K39: PK autoincremental
A40: 2 | B40: codigo | C40: Código institucional del programa | D40: CARACTER | E40: VARCHAR(20) | F40: VARCHAR(20) | G40: No | J40: S | K40: Valor único
A41: 3 | B41: nombre | C41: Nombre completo del programa académico | D41: CARACTER | E41: VARCHAR(150) | F41: VARCHAR(150) | G41: No
A42: 4 | B42: facultad | C42: Facultad a la que pertenece el programa | D42: CARACTER | E42: VARCHAR(100) | F42: VARCHAR(100)
A43: 5 | B43: nivel | C43: Nivel académico (pregrado, posgrado, etc) | D43: CARACTER | E43: VARCHAR(50) | F43: VARCHAR(50)
A45: 2 | B45: Tabla | C45: =B6 -> habilidad | E45: Descripción Tabla | G45: =C6 -> Catálogo de habilidades que los usuarios pueden asociar a su perfil | K45: Versión | L45: 1
A46: # | B46: Campo | C46: Descripción Campo | D46: Tipo Genérico | E46: Tipo PostgreSQL | F46: Tamaño | G46: Nulo | H46: PK | I46: FK | J46: UK | K46: Nota/Comentarios
A47: 1 | B47: id_habilidad | C47: Identificador único de la habilidad | D47: AUTOINCREMENTABLE | E47: SERIAL | F47: SERIAL | G47: No | H47: S | K47: PK autoincremental
A48: 2 | B48: nombre | C48: Nombre de la habilidad | D48: CARACTER | E48: VARCHAR(100) | F48: VARCHAR(100) | G48: No | J48: S | K48: Valor único
A49: 3 | B49: categoria | C49: Categoría temática de la habilidad | D49: CARACTER | E49: VARCHAR(100) | F49: VARCHAR(100)
A51: 3 | B51: Tabla | C51: =B7 -> interes | E51: Descripción Tabla | G51: =C7 -> Catálogo de áreas de interés disponibles para los usuarios | K51: Versión | L51: 1
A52: # | B52: Campo | C52: Descripción Campo | D52: Tipo Genérico | E52: Tipo PostgreSQL | F52: Tamaño | G52: Nulo | H52: PK | I52: FK | J52: UK | K52: Nota/Comentarios
A53: 1 | B53: id_interes | C53: Identificador único del interés | D53: AUTOINCREMENTABLE | E53: SERIAL | F53: SERIAL | G53: No | H53: S | K53: PK autoincremental
A54: 2 | B54: nombre | C54: Nombre del área de interés | D54: CARACTER | E54: VARCHAR(100) | F54: VARCHAR(100) | G54: No | J54: S | K54: Valor único
A55: 3 | B55: categoria | C55: Categoría temática del interés | D55: CARACTER | E55: VARCHAR(100) | F55: VARCHAR(100)
A57: 4 | B57: Tabla | C57: =B8 -> empresa | E57: Descripción Tabla | G57: =C8 -> Empresas registradas en la plataforma para publicar ofertas laborales | K57: Versión | L57: 1
A58: # | B58: Campo | C58: Descripción Campo | D58: Tipo Genérico | E58: Tipo PostgreSQL | F58: Tamaño | G58: Nulo | H58: PK | I58: FK | J58: UK | K58: Nota/Comentarios
A59: 1 | B59: id_empresa | C59: Identificador único de la empresa | D59: AUTOINCREMENTABLE | E59: SERIAL | F59: SERIAL | G59: No | H59: S | K59: PK autoincremental
A60: 2 | B60: nombre | C60: Nombre o razón social de la empresa | D60: CARACTER | E60: VARCHAR(150) | F60: VARCHAR(150) | G60: No
A61: 3 | B61: descripcion | C61: Descripción general de la empresa | D61: TEXTO | E61: TEXT | F61: TEXT
A62: 4 | B62: sitio_web | C62: URL del sitio web corporativo | D62: URL | E62: VARCHAR(255) | F62: VARCHAR(255)
A63: 5 | B63: contacto | C63: Nombre o email del contacto en la empresa | D63: CARACTER | E63: VARCHAR(150) | F63: VARCHAR(150)
A65: 5 | B65: Tabla | C65: =B9 -> usuario | E65: Descripción Tabla | G65: =C9 -> Supertipo que agrupa a todos los tipos de usuarios de la red social | K65: Versión | L65: 1
A66: # | B66: Campo | C66: Descripción Campo | D66: Tipo Genérico | E66: Tipo PostgreSQL | F66: Tamaño | G66: Nulo | H66: PK | I66: FK | J66: UK | K66: Nota/Comentarios
A67: 1 | B67: id_usuario | C67: Identificador único del usuario | D67: AUTOINCREMENTABLE | E67: SERIAL | F67: SERIAL | G67: No | H67: S | K67: PK autoincremental
A68: 2 | B68: nombre | C68: Nombre(s) del usuario | D68: CARACTER | E68: VARCHAR(100) | F68: VARCHAR(100)
A69: 3 | B69: apellido | C69: Apellido(s) del usuario | D69: CARACTER | E69: VARCHAR(100) | F69: VARCHAR(100)
A70: 4 | B70: email | C70: Correo electrónico del usuario | D70: CARACTER | E70: VARCHAR(150) | F70: VARCHAR(150) | G70: No | J70: S | K70: Valor único
A71: 5 | B71: contrasena | C71: Hash de la contraseña del usuario | D71: CARACTER | E71: VARCHAR(255) | F71: VARCHAR(255) | K71: Almacenar hash, nunca texto plano
A72: 6 | B72: fecha_registro | C72: Fecha y hora de registro en la plataforma | D72: FECHA_HORA | E72: TIMESTAMP | F72: TIMESTAMP | K72: DEFAULT NOW()
A73: 7 | B73: foto_perfil | C73: URL de la foto de perfil del usuario | D73: URL | E73: VARCHAR(255) | F73: VARCHAR(255)
A74: 8 | B74: biografia | C74: Texto de presentación del usuario | D74: TEXTO | E74: TEXT | F74: TEXT
A75: 9 | B75: estado | C75: Estado de la cuenta (activo/inactivo/suspendido) | D75: ENUM | E75: VARCHAR(20) | F75: VARCHAR(20) | K75: DEFAULT 'activo'
A77: 6 | B77: Tabla | C77: =B10 -> estudiante | E77: Descripción Tabla | G77: =C10 -> Subtipo de usuario: estudiante activo de la institución | K77: Versión | L77: 1
A78: # | B78: Campo | C78: Descripción Campo | D78: Tipo Genérico | E78: Tipo PostgreSQL | F78: Tamaño | G78: Nulo | H78: PK | I78: FK | J78: UK | K78: Nota/Comentarios
A79: 1 | B79: id_usuario | C79: FK al supertipo usuario | D79: ENTERO | E79: INT | F79: INT | G79: No | H79: S | I79: S | K79: PK y FK a usuario
A80: 2 | B80: codigo_estudiante | C80: Código estudiantil institucional | D80: CARACTER | E80: VARCHAR(20) | F80: VARCHAR(20)
A81: 3 | B81: semestre | C81: Semestre actual cursado (1-10) | D81: ENTERO | E81: SMALLINT | F81: SMALLINT | K81: CHECK BETWEEN 1 AND 10
A82: 4 | B82: id_programa | C82: FK al programa académico del estudiante | D82: ENTERO | E82: INT | F82: INT | I82: S | K82: FK a programa_academico
A84: 7 | B84: Tabla | C84: =B11 -> docente | E84: Descripción Tabla | G84: =C11 -> Subtipo de usuario: docente vinculado a la institución | K84: Versión | L84: 1
A85: # | B85: Campo | C85: Descripción Campo | D85: Tipo Genérico | E85: Tipo PostgreSQL | F85: Tamaño | G85: Nulo | H85: PK | I85: FK | J85: UK | K85: Nota/Comentarios
A86: 1 | B86: id_usuario | C86: FK al supertipo usuario | D86: ENTERO | E86: INT | F86: INT | G86: No | H86: S | I86: S | K86: PK y FK a usuario
A87: 2 | B87: codigo_docente | C87: Código docente institucional | D87: CARACTER | E87: VARCHAR(20) | F87: VARCHAR(20)
A88: 3 | B88: departamento | C88: Departamento académico del docente | D88: CARACTER | E88: VARCHAR(100) | F88: VARCHAR(100)
A89: 4 | B89: especialidad | C89: Área de especialización del docente | D89: CARACTER | E89: VARCHAR(150) | F89: VARCHAR(150)
A91: 8 | B91: Tabla | C91: =B12 -> empleado | E91: Descripción Tabla | G91: =C12 -> Subtipo de usuario: empleado administrativo de la institución | K91: Versión | L91: 1
A92: # | B92: Campo | C92: Descripción Campo | D92: Tipo Genérico | E92: Tipo PostgreSQL | F92: Tamaño | G92: Nulo | H92: PK | I92: FK | J92: UK | K92: Nota/Comentarios
A93: 1 | B93: id_usuario | C93: FK al supertipo usuario | D93: ENTERO | E93: INT | F93: INT | G93: No | H93: S | I93: S | K93: PK y FK a usuario
A94: 2 | B94: codigo_empleado | C94: Código de empleado institucional | D94: CARACTER | E94: VARCHAR(20) | F94: VARCHAR(20)
A95: 3 | B95: cargo | C95: Cargo o puesto del empleado | D95: CARACTER | E95: VARCHAR(100) | F95: VARCHAR(100)
A96: 4 | B96: dependencia | C96: Dependencia o área administrativa | D96: CARACTER | E96: VARCHAR(150) | F96: VARCHAR(150)
A98: 9 | B98: Tabla | C98: =B13 -> egresado | E98: Descripción Tabla | G98: =C13 -> Subtipo de usuario: graduado de la institución | K98: Versión | L98: 1
A99: # | B99: Campo | C99: Descripción Campo | D99: Tipo Genérico | E99: Tipo PostgreSQL | F99: Tamaño | G99: Nulo | H99: PK | I99: FK | J99: UK | K99: Nota/Comentarios
A100: 1 | B100: id_usuario | C100: FK al supertipo usuario | D100: ENTERO | E100: INT | F100: INT | G100: No | H100: S | I100: S | K100: PK y FK a usuario
A101: 2 | B101: anio_egreso | C101: Año de graduación del egresado | D101: ENTERO | E101: SMALLINT | F101: SMALLINT
A102: 3 | B102: cargo_actual | C102: Cargo que ocupa actualmente | D102: CARACTER | E102: VARCHAR(100) | F102: VARCHAR(100)
A103: 4 | B103: empresa_actual | C103: Empresa donde trabaja actualmente | D103: CARACTER | E103: VARCHAR(150) | F103: VARCHAR(150)
A104: 5 | B104: id_programa | C104: FK al programa del que se graduó | D104: ENTERO | E104: INT | F104: INT | I104: S | K104: FK a programa_academico
A106: 10 | B106: Tabla | C106: =B14 -> publico_general | E106: Descripción Tabla | G106: =C14 -> Subtipo de usuario: persona externa sin vínculo institucional formal | K106: Versión | L106: 1
A107: # | B107: Campo | C107: Descripción Campo | D107: Tipo Genérico | E107: Tipo PostgreSQL | F107: Tamaño | G107: Nulo | H107: PK | I107: FK | J107: UK | K107: Nota/Comentarios
A108: 1 | B108: id_usuario | C108: FK al supertipo usuario | D108: ENTERO | E108: INT | F108: INT | G108: No | H108: S | I108: S | K108: PK y FK a usuario
A109: 2 | B109: organizacion | C109: Organización a la que pertenece | D109: CARACTER | E109: VARCHAR(150) | F109: VARCHAR(150)
A110: 3 | B110: tipo_vinculo | C110: Tipo de vínculo con la institución | D110: CARACTER | E110: VARCHAR(100) | F110: VARCHAR(100)
A112: 11 | B112: Tabla | C112: =B15 -> usuario_habilidad | E112: Descripción Tabla | G112: =C15 -> Tabla pivote N:M entre usuario y habilidad | K112: Versión | L112: 1
A113: # | B113: Campo | C113: Descripción Campo | D113: Tipo Genérico | E113: Tipo PostgreSQL | F113: Tamaño | G113: Nulo | H113: PK | I113: FK | J113: UK | K113: Nota/Comentarios
A114: 1 | B114: id_usuario | C114: FK al usuario | D114: ENTERO | E114: INT | F114: INT | G114: No | H114: S | I114: S | K114: PK compuesta
A115: 2 | B115: id_habilidad | C115: FK a la habilidad | D115: ENTERO | E115: INT | F115: INT | G115: No | H115: S | I115: S | K115: PK compuesta
A117: 12 | B117: Tabla | C117: =B16 -> usuario_interes | E117: Descripción Tabla | G117: =C16 -> Tabla pivote N:M entre usuario y área de interés | K117: Versión | L117: 1
A118: # | B118: Campo | C118: Descripción Campo | D118: Tipo Genérico | E118: Tipo PostgreSQL | F118: Tamaño | G118: Nulo | H118: PK | I118: FK | J118: UK | K118: Nota/Comentarios
A119: 1 | B119: id_usuario | C119: FK al usuario | D119: ENTERO | E119: INT | F119: INT | G119: No | H119: S | I119: S | K119: PK compuesta
A120: 2 | B120: id_interes | C120: FK al interés | D120: ENTERO | E120: INT | F120: INT | G120: No | H120: S | I120: S | K120: PK compuesta
A122: 13 | B122: Tabla | C122: =B17 -> seguimiento | E122: Descripción Tabla | G122: =C17 -> Relación reflexiva N:M que modela el seguimiento entre usuarios | K122: Versión | L122: 1
A123: # | B123: Campo | C123: Descripción Campo | D123: Tipo Genérico | E123: Tipo PostgreSQL | F123: Tamaño | G123: Nulo | H123: PK | I123: FK | J123: UK | K123: Nota/Comentarios
A124: 1 | B124: id_seguidor | C124: FK al usuario que sigue | D124: ENTERO | E124: INT | F124: INT | G124: No | H124: S | I124: S | K124: PK compuesta
A125: 2 | B125: id_seguido | C125: FK al usuario seguido | D125: ENTERO | E125: INT | F125: INT | G125: No | H125: S | I125: S | K125: PK compuesta; CHECK id_seguidor <> id_seguido
A126: 3 | B126: fecha_ingreso | C126: Fecha en que se estableció el seguimiento | D126: FECHA_HORA | E126: TIMESTAMP | F126: TIMESTAMP | K126: DEFAULT NOW()
A128: 14 | B128: Tabla | C128: =B18 -> grupo | E128: Descripción Tabla | G128: =C18 -> Grupos creados por usuarios para organizar actividades colectivas | K128: Versión | L128: 1
A129: # | B129: Campo | C129: Descripción Campo | D129: Tipo Genérico | E129: Tipo PostgreSQL | F129: Tamaño | G129: Nulo | H129: PK | I129: FK | J129: UK | K129: Nota/Comentarios
A130: 1 | B130: id_grupo | C130: Identificador único del grupo | D130: AUTOINCREMENTABLE | E130: SERIAL | F130: SERIAL | G130: No | H130: S | K130: PK autoincremental
A131: 2 | B131: id_creador | C131: FK al usuario creador del grupo | D131: ENTERO | E131: INT | F131: INT | G131: No | I131: S | K131: FK a usuario
A132: 3 | B132: nombre | C132: Nombre del grupo | D132: CARACTER | E132: VARCHAR(150) | F132: VARCHAR(150) | G132: No
...
